ruon/__init__.py
ruon/exception.py
ruon/option.py
ruon/result.py
ruon/version.py
ruon-0.0.2.post1.dist-info/METADATA
ruon-0.0.2.post1.dist-info/WHEEL
ruon-0.0.2.post1.dist-info/licenses/LICENSE
ruon-0.0.2.post1.dist-info/RECORD
