Metadata-Version: 2.4
Name: ruon
Version: 0.0.2.post1
Summary: Implement some data structures and algorithms used in Rust for Python
Project-URL: Homepage, https://github.com/wangzhen0518/ruon
Project-URL: Issues, https://github.com/wangzhen0518/ruon/issues
Author-email: Zhen Wang <wangzhen0518@126.com>
License-File: LICENSE
Classifier: Operating System :: OS Independent
Classifier: Programming Language :: Python :: 3
Requires-Python: >=3.0
